ShiyanlouAndroidJiaochengHeji20160904/README.md
ShiyanlouAndroidJiaochengHeji20160904/__init__.py
ShiyanlouAndroidJiaochengHeji20160904/__main__.py
ShiyanlouAndroidJiaochengHeji20160904/file.epub
ShiyanlouAndroidJiaochengHeji20160904/index.html
ShiyanlouAndroidJiaochengHeji20160904/css/__init__.py
ShiyanlouAndroidJiaochengHeji20160904/css/annotations.css
ShiyanlouAndroidJiaochengHeji20160904/css/main.css
ShiyanlouAndroidJiaochengHeji20160904/css/normalize.css
ShiyanlouAndroidJiaochengHeji20160904/css/popup.css
ShiyanlouAndroidJiaochengHeji20160904/font/__init__.py
ShiyanlouAndroidJiaochengHeji20160904/font/fontello.eot
ShiyanlouAndroidJiaochengHeji20160904/font/fontello.svg
ShiyanlouAndroidJiaochengHeji20160904/font/fontello.ttf
ShiyanlouAndroidJiaochengHeji20160904/font/fontello.woff
ShiyanlouAndroidJiaochengHeji20160904/img/__init__.py
ShiyanlouAndroidJiaochengHeji20160904/img/annotator-glyph-sprite.png
ShiyanlouAndroidJiaochengHeji20160904/img/annotator-icon-sprite.png
ShiyanlouAndroidJiaochengHeji20160904/img/apple-touch-icon.png
ShiyanlouAndroidJiaochengHeji20160904/img/cancelfullscreen.png
ShiyanlouAndroidJiaochengHeji20160904/img/close.png
ShiyanlouAndroidJiaochengHeji20160904/img/fullscreen.png
ShiyanlouAndroidJiaochengHeji20160904/img/loader.gif
ShiyanlouAndroidJiaochengHeji20160904/img/menu-icon.png
ShiyanlouAndroidJiaochengHeji20160904/img/save.png
ShiyanlouAndroidJiaochengHeji20160904/img/saved.png
ShiyanlouAndroidJiaochengHeji20160904/img/settings-s.png
ShiyanlouAndroidJiaochengHeji20160904/img/settings.png
ShiyanlouAndroidJiaochengHeji20160904/img/star.png
ShiyanlouAndroidJiaochengHeji20160904/js/__init__.py
ShiyanlouAndroidJiaochengHeji20160904/js/epub.js
ShiyanlouAndroidJiaochengHeji20160904/js/epub.min.js
ShiyanlouAndroidJiaochengHeji20160904/js/epub.min.map
ShiyanlouAndroidJiaochengHeji20160904/js/hooks.min.js
ShiyanlouAndroidJiaochengHeji20160904/js/hooks.min.map
ShiyanlouAndroidJiaochengHeji20160904/js/reader.js
shiyanlou_android_jiaocheng_heji_20160904-2024.3.1.0.dist-info/METADATA
shiyanlou_android_jiaocheng_heji_20160904-2024.3.1.0.dist-info/WHEEL
shiyanlou_android_jiaocheng_heji_20160904-2024.3.1.0.dist-info/entry_points.txt
shiyanlou_android_jiaocheng_heji_20160904-2024.3.1.0.dist-info/top_level.txt
shiyanlou_android_jiaocheng_heji_20160904-2024.3.1.0.dist-info/RECORD
